digitalhub_runtime_flower/__init__.py
digitalhub_runtime_flower/entities/__init__.py
digitalhub_runtime_flower/entities/_base/__init__.py
digitalhub_runtime_flower/entities/_base/runtime_entity/__init__.py
digitalhub_runtime_flower/entities/_base/runtime_entity/builder.py
digitalhub_runtime_flower/entities/_commons/__init__.py
digitalhub_runtime_flower/entities/_commons/enums.py
digitalhub_runtime_flower/entities/function/__init__.py
digitalhub_runtime_flower/entities/function/_base/__init__.py
digitalhub_runtime_flower/entities/function/_base/builder.py
digitalhub_runtime_flower/entities/function/_base/entity.py
digitalhub_runtime_flower/entities/function/_base/models.py
digitalhub_runtime_flower/entities/function/_base/spec.py
digitalhub_runtime_flower/entities/function/_base/status.py
digitalhub_runtime_flower/entities/function/flower_app/__init__.py
digitalhub_runtime_flower/entities/function/flower_app/builder.py
digitalhub_runtime_flower/entities/function/flower_app/entity.py
digitalhub_runtime_flower/entities/function/flower_app/models.py
digitalhub_runtime_flower/entities/function/flower_app/spec.py
digitalhub_runtime_flower/entities/function/flower_app/status.py
digitalhub_runtime_flower/entities/function/flower_app/utils.py
digitalhub_runtime_flower/entities/function/flower_client/__init__.py
digitalhub_runtime_flower/entities/function/flower_client/builder.py
digitalhub_runtime_flower/entities/function/flower_client/entity.py
digitalhub_runtime_flower/entities/function/flower_client/spec.py
digitalhub_runtime_flower/entities/function/flower_client/status.py
digitalhub_runtime_flower/entities/function/flower_server/__init__.py
digitalhub_runtime_flower/entities/function/flower_server/builder.py
digitalhub_runtime_flower/entities/function/flower_server/entity.py
digitalhub_runtime_flower/entities/function/flower_server/spec.py
digitalhub_runtime_flower/entities/function/flower_server/status.py
digitalhub_runtime_flower/entities/run/__init__.py
digitalhub_runtime_flower-0.14.0.dist-info/METADATA
digitalhub_runtime_flower-0.14.0.dist-info/WHEEL
digitalhub_runtime_flower-0.14.0.dist-info/licenses/AUTHORS
digitalhub_runtime_flower-0.14.0.dist-info/licenses/LICENSE
digitalhub_runtime_flower-0.14.0.dist-info/RECORD
