Metadata-Version: 2.4
Name: digitalhub-runtime-flower
Version: 0.14.0
Summary: Flower runtime for DHCore
Project-URL: Homepage, https://github.com/scc-digitalhub/digitalhub-sdk-runtime-flower
Author-email: Fondazione Bruno Kessler <digitalhub@fbk.eu>, Matteo Martini <mmartini@fbk.eu>
License:                                  Apache License
License-File: AUTHORS
License-File: LICENSE
Keywords: data,dataops,kubernetes
Classifier: License :: OSI Approved :: Apache Software License
Classifier: Programming Language :: Python :: 3.9
Classifier: Programming Language :: Python :: 3.10
Classifier: Programming Language :: Python :: 3.11
Classifier: Programming Language :: Python :: 3.12
Requires-Python: <3.13,>=3.9
Requires-Dist: digitalhub<0.15,>=0.14.0b
Provides-Extra: dev
Requires-Dist: digitalhub[dev]<0.15,>=0.14.0b; extra == 'dev'
Provides-Extra: local
Requires-Dist: flwr[simulation]; extra == 'local'
